MANIFEST.in
README.rst
setup.py
slimoore/__init__.py
slimoore/admin.py
slimoore/apps.py
slimoore/models.py
slimoore/tests.py
slimoore/urls.py
slimoore/views.py
slimoore.egg-info/PKG-INFO
slimoore.egg-info/SOURCES.txt
slimoore.egg-info/dependency_links.txt
slimoore.egg-info/top_level.txt
slimoore/static/inspinia/css/animate.css
slimoore/static/inspinia/css/bootstrap.css
slimoore/static/inspinia/css/bootstrap.css.map
slimoore/static/inspinia/css/bootstrap.min.css
slimoore/static/inspinia/css/bootstrap.min.css.map
slimoore/static/inspinia/css/style.css
slimoore/static/inspinia/css/patterns/1.png
slimoore/static/inspinia/css/patterns/2.png
slimoore/static/inspinia/css/patterns/3.png
slimoore/static/inspinia/css/patterns/4.png
slimoore/static/inspinia/css/patterns/5.png
slimoore/static/inspinia/css/patterns/6.png
slimoore/static/inspinia/css/patterns/7.png
slimoore/static/inspinia/css/patterns/congruent_pentagon.png
slimoore/static/inspinia/css/patterns/header-profile-skin-1.png
slimoore/static/inspinia/css/patterns/header-profile-skin-2.png
slimoore/static/inspinia/css/patterns/header-profile-skin-3.png
slimoore/static/inspinia/css/patterns/header-profile.png
slimoore/static/inspinia/css/patterns/otis_redding.png
slimoore/static/inspinia/css/patterns/shattered.png
slimoore/static/inspinia/css/patterns/triangular.png
slimoore/static/inspinia/css/plugins/awesome-bootstrap-checkbox/awesome-bootstrap-checkbox.css
slimoore/static/inspinia/css/plugins/blueimp/css/blueimp-gallery-indicator.css
slimoore/static/inspinia/css/plugins/blueimp/css/blueimp-gallery-video.css
slimoore/static/inspinia/css/plugins/blueimp/css/blueimp-gallery.css
slimoore/static/inspinia/css/plugins/blueimp/css/blueimp-gallery.min.css
slimoore/static/inspinia/css/plugins/blueimp/css/demo.css
slimoore/static/inspinia/css/plugins/blueimp/img/error.png
slimoore/static/inspinia/css/plugins/blueimp/img/error.svg
slimoore/static/inspinia/css/plugins/blueimp/img/loading.gif
slimoore/static/inspinia/css/plugins/blueimp/img/play-pause.png
slimoore/static/inspinia/css/plugins/blueimp/img/play-pause.svg
