Metadata-Version: 1.0
Name: slimoore
Version: 0.1.6
Summary: A simple Django app to conduct Web-based polls.
Home-page: https://https://github.com/lizidashen/
Author: sinf
Author-email: xinguanhua@gmail.com
License: UNKNOWN
Platform: UNKNOWN
